querymodelling/__helper__.py
querymodelling/__init__.py
querymodelling/__version__.py
querymodelling/base.py
querymodelling/fields.py
querymodelling/model.py
querymodelling/pydantic.py
querymodelling/redis_om.py
querymodelling/sql.py
querymodelling-0.0.14.dist-info/licenses/AUTHORS.rst
querymodelling-0.0.14.dist-info/licenses/LICENSE
tests/__init__.py
tests/__main__.py
tests/basic_test.py
querymodelling-0.0.14.dist-info/METADATA
querymodelling-0.0.14.dist-info/WHEEL
querymodelling-0.0.14.dist-info/top_level.txt
querymodelling-0.0.14.dist-info/RECORD
