Metadata-Version: 2.4
Name: querymodelling
Version: 0.0.14
Summary: build consistent api query models for fastapi
Author: George Haddad
Author-email: George Haddad <georgeh87@live.de>
License:                                  Apache License
Requires-Python: >=3.11
License-File: LICENSE
License-File: AUTHORS.rst
Requires-Dist: pydantic>=2.10.5
Dynamic: author
Dynamic: license-file
